llm_tooluse/__init__.py
llm_tooluse/calculator.py
llm_tooluse/llm.py
llm_tooluse/main.py
llm_tooluse/schemagenerators.py
llm_tooluse/settings.py
llm_tooluse/tools.py
llm_tooluse-0.1.0.dist-info/METADATA
llm_tooluse-0.1.0.dist-info/WHEEL
llm_tooluse-0.1.0.dist-info/entry_points.txt
llm_tooluse-0.1.0.dist-info/RECORD
