Metadata-Version: 2.4
Name: llm_tooluse
Version: 0.1.0
Summary: Automate tooluse with LLMs
Author-email: raoul grouls <Raoul.Grouls@han.nl>
Requires-Python: >=3.11
Requires-Dist: anthropic>=0.42.0
Requires-Dist: loguru>=0.7.3
Requires-Dist: ollama>=0.4.5
Requires-Dist: python-dotenv>=1.0.1
Provides-Extra: demo
Requires-Dist: sqlalchemy>=2.0.38; extra == 'demo'
